chemnlp/__init__.py
chemnlp/classification/__init__.py
chemnlp/classification/bert_classify.py
chemnlp/classification/gnn_class.py
chemnlp/classification/scikit_class.py
chemnlp/clustering/__init__.py
chemnlp/clustering/tsne.py
chemnlp/utils/__init__.py
chemnlp/utils/keywords.py
chemnlp/utils/process_doc.py
chemnlp/utils/run_chemnlp.py
chemnlp/wordcloud/__init__.py
chemnlp/wordcloud/make_wordcloud.py
chemnlp-2023.7.1.data/scripts/run_chemnlp.py
chemnlp-2023.7.1.dist-info/LICENSE
chemnlp-2023.7.1.dist-info/METADATA
chemnlp-2023.7.1.dist-info/WHEEL
chemnlp-2023.7.1.dist-info/top_level.txt
chemnlp-2023.7.1.dist-info/RECORD
