Metadata-Version: 2.1
Name: chemnlp
Version: 2023.7.1
Summary: chemnlp
Home-page: https://github.com/usnistgov/chemnlp
Author: Kamal Choudhary
Author-email: kamal.choudhary@nist.gov
Classifier: Programming Language :: Python :: 3
Classifier: License :: OSI Approved :: MIT License
Classifier: Operating System :: OS Independent
Requires-Python: >=3.7
License-File: LICENSE
Requires-Dist: numpy >=1.22.0
Requires-Dist: scipy >=1.6.3
Requires-Dist: jarvis-tools >=2021.07.19
Requires-Dist: ChemDataExtractor >=1.3.0
Requires-Dist: matplotlib >=3.4.1
Requires-Dist: flake8 >=3.9.1
Requires-Dist: pycodestyle >=2.7.0
Requires-Dist: pydocstyle >=6.0.0
